odoo/addons/fieldservice_kanban_info_route/README.rst
odoo/addons/fieldservice_kanban_info_route/__init__.py
odoo/addons/fieldservice_kanban_info_route/__manifest__.py
odoo/addons/fieldservice_kanban_info_route/i18n/ca.po
odoo/addons/fieldservice_kanban_info_route/i18n/es.po
odoo/addons/fieldservice_kanban_info_route/i18n/fieldservice_kanban_info_route.pot
odoo/addons/fieldservice_kanban_info_route/readme/CONTRIBUTORS.rst
odoo/addons/fieldservice_kanban_info_route/readme/DESCRIPTION.rst
odoo/addons/fieldservice_kanban_info_route/readme/USAGE.rst
odoo/addons/fieldservice_kanban_info_route/static/description/icon.png
odoo/addons/fieldservice_kanban_info_route/static/description/index.html
odoo/addons/fieldservice_kanban_info_route/views/fsm_order.xml
odoo_addon_fieldservice_kanban_info_route-15.0.1.0.0.2.dist-info/METADATA
odoo_addon_fieldservice_kanban_info_route-15.0.1.0.0.2.dist-info/WHEEL
odoo_addon_fieldservice_kanban_info_route-15.0.1.0.0.2.dist-info/top_level.txt
odoo_addon_fieldservice_kanban_info_route-15.0.1.0.0.2.dist-info/RECORD
