Metadata-Version: 2.1
Name: odoo-addon-fieldservice_kanban_info_route
Version: 15.0.1.0.0.2
Summary: Display route information on Field Service Kanban cards.
Home-page: https://github.com/OCA/field-service
Author: APSL-Nagarro, Odoo Community Association (OCA)
Author-email: support@odoo-community.org
License: AGPL-3
Classifier: Programming Language :: Python
Classifier: Framework :: Odoo
Classifier: Framework :: Odoo :: 15.0
Classifier: License :: OSI Approved :: GNU Affero General Public License v3
Requires-Python: >=3.8
Requires-Dist: odoo-addon-fieldservice-kanban-info<15.1dev,>=15.0dev
Requires-Dist: odoo-addon-fieldservice-route<15.1dev,>=15.0dev
Requires-Dist: odoo<15.1dev,>=15.0a
